timi_pinyin
