Metadata-Version: 2.1
Name: timi-pinyin
Version: 1.0.2
Summary: 根据传入的input_str="费家村设备01", 返回该字符串的所有字符的拼音首字目组成的字符串: "fjcsb01".
Home-page: http://github.com/lxl0928/timi_pinyin
Author: Timi long
Author-email: lixiaolong@smuer.cn
License: UNKNOWN
Platform: UNKNOWN
Classifier: Development Status :: 5 - Production/Stable
Classifier: Intended Audience :: Developers
Classifier: License :: OSI Approved :: BSD License
Classifier: Operating System :: OS Independent
Classifier: Programming Language :: Python
Classifier: Programming Language :: Python :: 2.6
Classifier: Programming Language :: Python :: 2.7
Classifier: Programming Language :: Python :: 3.3
Classifier: Programming Language :: Python :: 3.4
Classifier: Programming Language :: Python :: 3.5
Classifier: Programming Language :: Python :: 3.6
Classifier: Programming Language :: Python :: 3.7
Provides-Extra: pypinyin
